chelo/__init__.py
chelo/base.py
chelo/registry.py
chelo/datasets/__init__.py
chelo/datasets/ames_mutagenicity.py
chelo/datasets/bc_factor.py
chelo/datasets/coal_fired_plant.py
chelo/datasets/cstr_dataset.py
chelo/datasets/opsd_pv_dataset.py
chelo/datasets/vapor_pressure.py
chelo/datasets/vle.py
chelo/datasets/wine_quality.py
chelo/utils/__init__.py
chelo/utils/cache_manager.py
chelo/utils/checksum.py
chelo/utils/config.py
chelo/utils/downloader.py
chelo/utils/kaggle_downloader.py
chelo-0.0.5.dist-info/licenses/LICENSE
chelo-0.0.5.dist-info/METADATA
chelo-0.0.5.dist-info/WHEEL
chelo-0.0.5.dist-info/top_level.txt
chelo-0.0.5.dist-info/RECORD
