Metadata-Version: 2.4
Name: chelo
Version: 0.0.5
Summary: Chemical Engineering Dataset Loader Library
Author-email: Nikolaos Passalis <passalis@auth.gr>
License: MIT License
Classifier: Programming Language :: Python :: 3
Classifier: License :: OSI Approved :: MIT License
Classifier: Operating System :: OS Independent
License-File: LICENSE
Requires-Dist: numpy
Requires-Dist: pandas
Requires-Dist: tqdm
Requires-Dist: requests
Requires-Dist: kaggle
Requires-Dist: openpyxl
Requires-Dist: joblib
Dynamic: license-file
